minecode_pipelines/README.rst
minecode_pipelines/__init__.py
minecode_pipelines/miners/__init__.py
minecode_pipelines/miners/cpan.py
minecode_pipelines/miners/npm.py
minecode_pipelines/miners/pypi.py
minecode_pipelines/pipelines/__init__.py
minecode_pipelines/pipelines/mine_alpine.py
minecode_pipelines/pipelines/mine_cargo.py
minecode_pipelines/pipelines/mine_composer.py
minecode_pipelines/pipelines/mine_conan.py
minecode_pipelines/pipelines/mine_cpan.py
minecode_pipelines/pipelines/mine_cran.py
minecode_pipelines/pipelines/mine_debian.py
minecode_pipelines/pipelines/mine_maven.py
minecode_pipelines/pipelines/mine_npm.py
minecode_pipelines/pipelines/mine_nuget.py
minecode_pipelines/pipelines/mine_pypi.py
minecode_pipelines/pipelines/mine_swift.py
minecode_pipelines/pipes/__init__.py
minecode_pipelines/pipes/alpine.py
minecode_pipelines/pipes/cargo.py
minecode_pipelines/pipes/composer.py
minecode_pipelines/pipes/conan.py
minecode_pipelines/pipes/cpan.py
minecode_pipelines/pipes/cran.py
minecode_pipelines/pipes/debian.py
minecode_pipelines/pipes/java_stream.py
minecode_pipelines/pipes/java_stream.py.ABOUT
minecode_pipelines/pipes/java_stream.py.LICENSE
minecode_pipelines/pipes/ls.py
minecode_pipelines/pipes/maven.py
minecode_pipelines/pipes/npm.py
minecode_pipelines/pipes/nuget.py
minecode_pipelines/pipes/pypi.py
minecode_pipelines/pipes/swift.py
minecode_pipelines/utils.py
minecode_pipelines-0.1.1.dist-info/entry_points.txt
minecode_pipelines-0.1.1.dist-info/WHEEL
minecode_pipelines-0.1.1.dist-info/METADATA
minecode_pipelines-0.1.1.dist-info/NOTICE
minecode_pipelines-0.1.1.dist-info/apache-2.0.LICENSE
minecode_pipelines-0.1.1.dist-info/RECORD
