Metadata-Version: 2.1
Name: minecode_pipelines
Version: 0.1.1
Summary: A library for mining packageURLs and package metadata from ecosystem repositories.
Keywords: purl,Package-URL,open source,package,sca,scan,index,federated,data
Author-email: "AboutCode, nexB Inc. and others" <info@aboutcode.org>
Requires-Python: >=3.10
Classifier: Development Status :: 4 - Beta
Classifier: Intended Audience :: Developers
Classifier: Programming Language :: Python :: 3
Classifier: Programming Language :: Python :: 3 :: Only
Classifier: Topic :: Software Development
Classifier: Topic :: Utilities
Requires-Dist: aboutcode.hashid >= 0.2.0
Requires-Dist: aboutcode.federated >= 0.1.0
Requires-Dist: packageurl_python >= 0.15.6
Requires-Dist: scancodeio >= 35.3.0
Requires-Dist: ftputil >= 5.1.0
Requires-Dist: jawa >= 2.2.0
Requires-Dist: arrow >= 1.3.0
Requires-Dist: beautifulsoup4 >= 4.13.4
Project-URL: Homepage, https://github.com/aboutcode-org/purldb
